README.md
setup.py
lbrlabs_pulumi_tailscalebastion/__init__.py
lbrlabs_pulumi_tailscalebastion/_utilities.py
lbrlabs_pulumi_tailscalebastion/provider.py
lbrlabs_pulumi_tailscalebastion/pulumi-plugin.json
lbrlabs_pulumi_tailscalebastion/py.typed
lbrlabs_pulumi_tailscalebastion.egg-info/PKG-INFO
lbrlabs_pulumi_tailscalebastion.egg-info/SOURCES.txt
lbrlabs_pulumi_tailscalebastion.egg-info/dependency_links.txt
lbrlabs_pulumi_tailscalebastion.egg-info/not-zip-safe
lbrlabs_pulumi_tailscalebastion.egg-info/requires.txt
lbrlabs_pulumi_tailscalebastion.egg-info/top_level.txt
lbrlabs_pulumi_tailscalebastion/aws/__init__.py
lbrlabs_pulumi_tailscalebastion/aws/bastion.py
lbrlabs_pulumi_tailscalebastion/azure/__init__.py
lbrlabs_pulumi_tailscalebastion/azure/bastion.py
lbrlabs_pulumi_tailscalebastion/kubernetes/__init__.py
lbrlabs_pulumi_tailscalebastion/kubernetes/bastion.py