Metadata-Version: 2.1
Name: lbrlabs-pulumi-tailscalebastion
Version: 0.9.0
Summary: A Pulumi package for creating a tailscale bastion in AWS.
Project-URL: Repository, https://github.com/lbrlabs/pulumi-tailscale-bastion
Keywords: aws tailscale lbrlabs kind/component category/network
Requires-Python: >=3.9
